flask_styleguide/__init__.py
flask_styleguide/compat.py
flask_styleguide/core.py
flask_styleguide/jinjaext.py
Flask_Styleguide-0.4.0.dist-info/DESCRIPTION.rst
Flask_Styleguide-0.4.0.dist-info/METADATA
Flask_Styleguide-0.4.0.dist-info/metadata.json
Flask_Styleguide-0.4.0.dist-info/RECORD
Flask_Styleguide-0.4.0.dist-info/top_level.txt
Flask_Styleguide-0.4.0.dist-info/WHEEL
