Metadata-Version: 2.0
Name: Flask-Styleguide
Version: 0.4.0
Summary: A living Styleguide for your Flask application.
Home-page: https://github.com/vitalk/flask-styleguide
Author: Vital Kudzelka
Author-email: vital.kudzelka@gmail.com
License: MIT
Download-URL: https://github.com/vitalk/flask-styleguide/tarball/0.4.0
Keywords: flask live styleguide
Platform: any
Classifier: Development Status :: 4 - Beta
Classifier: Environment :: Web Environment
Classifier: Intended Audience :: Developers
Classifier: License :: OSI Approved :: MIT License
Classifier: Operating System :: OS Independent
Classifier: Programming Language :: Python
Classifier: Programming Language :: Python :: 2
Classifier: Programming Language :: Python :: 2.6
Classifier: Programming Language :: Python :: 2.7
Classifier: Programming Language :: Python :: 3
Classifier: Programming Language :: Python :: 3.3
Classifier: Programming Language :: Python :: 3.4
Classifier: Programming Language :: Python :: Implementation :: CPython
Classifier: Programming Language :: Python :: Implementation :: PyPy
Classifier: Framework :: Flask
Classifier: Topic :: Internet :: WWW/HTTP :: Dynamic Content
Classifier: Topic :: Software Development :: Libraries :: Python Modules
Requires-Dist: Flask (>=0.10.1)
Requires-Dist: pykss (>=0.4)
Provides-Extra: test
Requires-Dist: pytest (>=2.5.2); extra == 'test'
Requires-Dist: pytest-cov (>=1.6); extra == 'test'
Requires-Dist: pytest-flask (>=0.10.0); extra == 'test'
